SettingsSmith/__init__.py
SettingsSmith/settings.py
settingssmith-0.1.0.dist-info/LICENSE
settingssmith-0.1.0.dist-info/METADATA
settingssmith-0.1.0.dist-info/WHEEL
settingssmith-0.1.0.dist-info/RECORD
