Metadata-Version: 2.1
Name: SettingsSmith
Version: 0.1.0
Summary: 
License: MIT
Author: Noah Gula
Author-email: noahrgula@gmail.com
Requires-Python: >=3.9,<3.12
Classifier: License :: OSI Approved :: MIT License
Classifier: Programming Language :: Python :: 3
Classifier: Programming Language :: Python :: 3.9
Classifier: Programming Language :: Python :: 3.10
Classifier: Programming Language :: Python :: 3.11
Requires-Dist: PySide6 (>=6.7.2,<7.0.0)
Requires-Dist: appdirs (>=1.4.4,<2.0.0)
